{
  "project_info": {
    "project_number": "410140670170",
    "project_id": "gru-mobil",
    "storage_bucket": "gru-mobil.appspot.com"
  },
  "client": [
    {
      "client_info": {
        "mobilesdk_app_id": "1:410140670170:android:2d3ffd98dc891d8c1ecde3",
        "android_client_info": {
          "package_name": "com.legionhamz.gru"
        }
      },
      "oauth_client": [
        {
          "client_id": "410140670170-tckap0rejnpsvlp36b5s15t325e41hu3.apps.googleusercontent.com",
          "client_type": 3
        }
      ],
      "api_key": [
        {
          "current_key": "AIzaSyCIwx_YjZN6snGuS_St4Q7kRmr-ism2JAM"
        }
      ],
      "services": {
        "appinvite_service": {
          "other_platform_oauth_client": [
            {
              "client_id": "410140670170-tckap0rejnpsvlp36b5s15t325e41hu3.apps.googleusercontent.com",
              "client_type": 3
            }
          ]
        }
      }
    }
  ],
  "configuration_version": "1"
}